{
    "toptitle":{
		"text":"掌上服务",
		"bgcolor":"bag-blue",
		"color":"text-fff "
	},
	
	"listdata":[
		{
			"type":"cation",
			"text":"网上政务大厅",
			"datalist":[
				{
					"img":"img/farenbanshi.png",
					"text":"法人办事"
				},
				{
					"img":"img/gerenbanshi.png",
					"text":"个人办事"
				},
				{
					"img":"img/shenpishixang.png",
					"text":"审批事项"
				},
				{
					"img":"img/fuwushixiang.png",
					"text":"服务事项"
				},
				{
					"img":"img/zhuangtaichaxun.png",
					"text":"状态查询"
				},
				{
					"img":"img/jieguofankui.png",
					"text":"结果反馈"
				},
				{
					"img":"img/banlidianchaxun.png",
					"text":"办理点查询"
				},
				{
					"img":"img/baiyulanzhushou.png",
					"text":"白玉兰助手"
				}
			]
		},
		{
			"type":"cation",
			"text":"我的服务",
			"alldata":{
				"text":"更多",
				"img":"img/right.png",
				"act":""
			},
			"datalist":[
				{
					"img":"img/jiaotongchuxing.png",
					"text":"交通出行"
				},
				{
					"img":"img/churujing.png",
					"text":"出入境",
					"act":"crj.html"
				},
				{
					"img":"img/hunyingyuyue.png",
					"text":"婚姻预约"
				},
				{
					"img":"img/jingqushishixinxi.png",
					"text":"景区实时信息"
				}
			]
		},
		{
			"type":"cation",
			"text":"猜您关注",
			"datalist":[
				{
					"img":"img/qixiangxinxi.png",
					"text":"气象信息"
				},
				{
					"img":"img/shishijiaotong.png",
					"text":"实时交通"
				},
				{
					"img":"img/gongjijingchaxun.png",
					"text":"公积金查询"
				},
				{
					"img":"img/shuiwufuwu.png",
					"text":"税务服务器"
				}
			]
		}
	],
	"menulist":[
		{
			"fouce":"active",
			"icon":"icon-shouyev1",
			"text":"掌上服务",
			"url":"index.html"
		},
		{
			"fouce":"",
			"icon":"icon-chuzuwo",
			"text":"指尖互动",
			"url":"index.html"
		},
		{
			"fouce":"",
			"icon":"icon-richengbiao",
			"text":"申边政务",
			"url":"index.html"
		},
		{
			"fouce":"",
			"icon":"icon-gerenzhongxin",
			"text":"我的",
			"url":"index.html"
		}
	]
}